README.md
setup.py
Public_Data_FormatChange/FirstTest.py
Public_Data_FormatChange/__init__.py
Public_Data_FormatChange.egg-info/PKG-INFO
Public_Data_FormatChange.egg-info/SOURCES.txt
Public_Data_FormatChange.egg-info/dependency_links.txt
Public_Data_FormatChange.egg-info/not-zip-safe
Public_Data_FormatChange.egg-info/top_level.txt