Metadata-Version: 1.2
Name: Public-Data-FormatChange
Version: 1.1.0
Summary: Data Format Change
Home-page: https://github.com/kwonhyucknae/Public_Data_FormatChange
Author: Kwon Hyeoknae & Park Duri
Author-email: kwonhucnae@gmail.com
License: UNKNOWN
Download-URL: https://github.com/kwonhyucknae/Public_Data_FormatChange/archive/1.0.tar.gz
Keywords: Public_Data,Format_Change
Platform: UNKNOWN
Requires-Python: >=3
